{"Employees":[{"IdentityId":"ae3ae294-16a5-496d-8048-e3196b8c833e","FullName":"Kong Sunlyheng","Position":"Mnager","CardNo":"123","Logs":[{"Id":"8ee0515a-4c3c-4520-9c2c-3a3c4b05b6ca","TimeStamp":"2023-06-23T12:35:19.5129505+09:00","TimeShift":0},{"Id":"935f1041-ab28-4cd4-9304-a71b893fef10","TimeStamp":"2023-06-23T12:35:24.482755+09:00","TimeShift":1}]},{"IdentityId":"aae2c169-54bf-4d4f-8fe3-d03dea533c32","FullName":"Sothealen","Position":"Marketing Manager","CardNo":"789","Logs":[]},{"IdentityId":"a0554cb1-c8ee-45c3-9418-fd78af91cf67","FullName":"kkkk","Position":"Cleaner","CardNo":"900","Logs":[]}]}